findata/__init__.py
findata-0.1.2.dist-info/LICENSE
findata-0.1.2.dist-info/METADATA
findata-0.1.2.dist-info/WHEEL
findata-0.1.2.dist-info/RECORD
