Metadata-Version: 2.1
Name: findata
Version: 0.1.2
Summary: financial data build and analysis tools
Home-page: https://github.com/santokalayil/findata
Author: Santo K Thomas
Author-email: santokalayil@gmail.com
Requires-Python: >=3.11,<4.0
Classifier: Programming Language :: Python :: 3
Classifier: Programming Language :: Python :: 3.11
Classifier: Programming Language :: Python :: 3.12
Requires-Dist: fastapi (>=0.109.2,<0.110.0)
Requires-Dist: matplotlib (>=3.8.3,<4.0.0)
Requires-Dist: openpyxl (>=3.1.2,<4.0.0)
Requires-Dist: pandas (>=2.2.0,<3.0.0)
Requires-Dist: pyarrow (>=15.0.0,<16.0.0)
Requires-Dist: pydantic (>=2.6.1,<3.0.0)
Requires-Dist: seaborn (>=0.13.2,<0.14.0)
Project-URL: Repository, https://github.com/santokalayil/findata
